combinational/oddparitydet_3bit/oddparity_3.v
module oddparity_3bit

(
  input x,y,z,
  output p
);

assign p= x^y^z ;

endmodule

combinational/oddparitydet_3bit/tb_oddparity_3.v
module tb_oddparity_3bit;
 reg x,y,z;
 wire p;

oddparity_3bit uut
( .x(x), .y(y), .z(z), .p(p) );

initial begin

$dumpfile("oddparity_dump");
$dumpvars(0,tb_oddparity_3bit);

$display("X|Y|Z|P");
$monitor("%b|%b|%b|%b",x,y,z,p);

x=0 ; y=0 ; z=0; #10
x=0 ; y=0 ; z=1; #10
x=0 ; y=1 ; z=0; #10
x=0 ; y=1 ; z=1; #10
x=1 ; y=0 ; z=0; #10
x=1 ; y=0 ; z=1; #10
x=1 ; y=1 ; z=0; #10
x=1 ; y=1 ; z=1; #10

$finish;

end 
endmodule

combinational/oddparitydet_3bit/oddparity_test.vcd
$date
	Tue Jul 14 10:00:35 2026
$end
$version
	Icarus Verilog
$end
$timescale
	1s
$end
$scope module tb_oddparity_3bit $end
$var wire 1 ! p $end
$var reg 1 " x $end
$var reg 1 # y $end
$var reg 1 $ z $end
$scope module uut $end
$var wire 1 ! p $end
$var wire 1 " x $end
$var wire 1 # y $end
$var wire 1 $ z $end
$upscope $end
$upscope $end
$enddefinitions $end
$comment Show the parameter values. $end
$dumpall
$end
#0
$dumpvars
0$
0#
0"
0!
$end
#10
1!
1$
#20
0$
1#
#30
0!
1$
#40
1!
0$
0#
1"
#50
0!
1$
#60
0$
1#
#70
1!
1$
