combinational/mux_8x1/mux_8x1.v
module mux_8x1
(input[7:0] i, 
 input x, 
 input y, 
 input z,
 output R);

assign R= (~x&~y&~z&i[0]) | (~x&~y&z&i[1]) | (~x&y&~z&i[2]) | (~x&y&z&i[3]) | (x&~y&~z&i[4]) | (x&~y&z&i[5]) | (x&y&~z&i[6]) | (x&y&z&i[7]); 

endmodule

combinational/mux_8x1/tb_mux_8x1.v
module tb_mux_8x1;

reg[7:0] i;
reg x;
reg y;
reg z;

wire R;


mux_8x1 uut (.i(i),.x(x),.y(y),.z(z),.R(R));

initial begin

    $dumpfile("tb_mux_8x1.vcd");
    $dumpvars(0, tb_mux_8x1);
    $display("X|Y|Z|R");
    $monitor("%b|%b|%b|%b", x, y, z, R);
    
    i = 8'b00100001;
    x = 1;
    y = 0;
    z = 0;

    x=0; y=0; z=0; #10;
    x=0; y=0; z=1; #10;
    x=0; y=1; z=0; #10;
    x=0; y=1; z=1; #10;
    x=1; y=0; z=0; #10;
    x=1; y=0; z=1; #10;
    x=1; y=1; z=0; #10;
    x=1; y=1; z=1; #10;

   $finish;

end
endmodule

combinational/mux_8x1/tb_mux_8x1.vcd
$date
	Mon Jul 13 23:36:19 2026
$end
$version
	Icarus Verilog
$end
$timescale
	1s
$end
$scope module tb_mux_8x1 $end
$var wire 1 ! R $end
$var reg 8 " i [7:0] $end
$var reg 1 # x $end
$var reg 1 $ y $end
$var reg 1 % z $end
$scope module uut $end
$var wire 1 ! R $end
$var wire 8 & i [7:0] $end
$var wire 1 # x $end
$var wire 1 $ y $end
$var wire 1 % z $end
$upscope $end
$upscope $end
$enddefinitions $end
$comment Show the parameter values. $end
$dumpall
$end
#0
$dumpvars
b100001 &
0%
0$
0#
b100001 "
1!
$end
#10
0!
1%
#20
0%
1$
#30
1%
#40
0%
0$
1#
#50
1!
1%
#60
0!
0%
1$
#70
1%
